AUTHORS
LICENSE
MANIFEST.in
README.rst
setup.cfg
setup.py
django_swingers.egg-info/PKG-INFO
django_swingers.egg-info/SOURCES.txt
django_swingers.egg-info/dependency_links.txt
django_swingers.egg-info/not-zip-safe
django_swingers.egg-info/requires.txt
django_swingers.egg-info/top_level.txt
docs/Makefile
docs/api.txt
docs/conf.py
docs/index.txt
docs/make.bat
docs/_ext/djangodocs.py
docs/_static/logo.png
docs/_templates/sidebarintro.html
docs/_templates/sidebarlogo.html
docs/_themes/.gitignore
docs/_themes/LICENSE
docs/_themes/README.rst
docs/_themes/flask_theme_support.py
docs/_themes/kr/layout.html
docs/_themes/kr/relations.html
docs/_themes/kr/theme.conf
docs/_themes/kr/static/flasky.css_t
docs/_themes/kr_small/layout.html
docs/_themes/kr_small/theme.conf
docs/_themes/kr_small/static/flasky.css_t
docs/dev/authors.txt
docs/dev/changelog.txt
docs/dev/contribute.txt
docs/dev/todo.txt
docs/user/admin.txt
docs/user/auth.txt
docs/user/base.txt
docs/user/bin.txt
docs/user/conf.txt
docs/user/forms.txt
docs/user/geo.txt
docs/user/install.txt
docs/user/intro.txt
docs/user/management.txt
docs/user/middleware.txt
docs/user/models.txt
docs/user/quickstart.txt
docs/user/templates.txt
docs/user/templatetags.txt
docs/user/utils.txt
docs/user/views.txt
swingers/__init__.py
swingers/compress.py
swingers/monitor.py
swingers/admin/__init__.py
swingers/admin/admin.py
swingers/admin/tests.py
swingers/admin/views.py
swingers/base/__init__.py
swingers/base/context_processors.py
swingers/base/tests.py
swingers/base/urls.py
swingers/bin/swingers-admin.py
swingers/conf/__init__.py
swingers/conf/project_template/.gitignore
swingers/conf/project_template/.gitignore.orig
swingers/conf/project_template/.hgignore
swingers/conf/project_template/AUTHORS
swingers/conf/project_template/DEBUG
swingers/conf/project_template/LICENSE
swingers/conf/project_template/MANIFEST.in
swingers/conf/project_template/README.rst
swingers/conf/project_template/envvars.txt
swingers/conf/project_template/setup.cfg
swingers/conf/project_template/setup.py
swingers/conf/project_template/docs/Makefile
swingers/conf/project_template/docs/conf.py
swingers/conf/project_template/docs/index.txt
swingers/conf/project_template/docs/make.bat
