Metadata-Version: 1.1
Name: django-swingers
Version: 1.1.1
Summary: Library of common utilities, templates and django customizations used throughout `Department of Parks and Wildlife <http://dpaw.wa.gov.au/>`_.
Home-page: https://bitbucket.org/dpaw/django-swingers
Author: Adon Metcalfe, Ashley Felton, Nick Sandford, Tomas Krajcaz
Author-email: adon.metcalfe@dpaw.wa.gov.au, ashley.felton@dpaw.wa.gov.au, nick.sandford@dpaw.wa.gov.au, tomas.krajca@dpaw.wa.gov.au
License: Apache License, Version 2.0
Keywords: django utilities authentication tools helpers dpaw
Platform: UNKNOWN
Classifier: Framework :: Django
Classifier: Intended Audience :: Developers
Classifier: Development Status :: 4 - Beta
Classifier: License :: OSI Approved :: Apache Software License
Classifier: Programming Language :: Python
Classifier: Programming Language :: Python :: 2
Classifier: Topic :: Software Development :: Libraries
Classifier: Topic :: Software Development :: Libraries :: Python Modules
